{
    "Name": "Onigiri",
    "Description": "A great snack for fishing. Rice balls wrapped in nori and stuffed with assorted meats.",
    "Category": "Cooking",
    "Edibility": 42,
    "EdibleIsDrink": false,
    "EdibleBuffs":
    {
        "Farming": 0,
        "Fishing": 2,
        "Mining": 0,
        "Luck": 1,
        "Foraging": 0,
        "MaxStamina": 0,
        "MagnetRadius": 0,
        "Speed": 0,
        "Defense": 0,
        "Attack": 0,
        "Duration": 172,
    },
    "Price": 1080,
    "IsColored": false,
    "Recipe":
    {
        "ResultCount": 1,
        "Ingredients": [
        {
            "Object": "Soy Sauce",
            "Count": 1,
        },
        {
            "Object": "Umeboshi",
            "Count": 1,
        },
        {
            "Object": 423,
            "Count": 1,
        },
        {
            "Object": 139,
            "Count": 1,
        },
        {
            "Object": 130,
            "Count": 1,
        },
        {
            "Object": 306,
            "Count": 1,
        }],
        "CanPurchase": true,
        "PurchaseFrom": "Sandy",
        "PurchasePrice": 2800,
        "PurchaseRequirements": null,
    },

    "GiftTastes":
    {
       "Love": ["Willy", "Sebastian", "Abigail", "Sophia", "Jas"],
       "Like": ["Linus", "Caroline", "Evelyn", "Emily", "Andy", "Sandy", "Pam", "Leah", "Penny",  "George", "Lewis", "Marnie", "Susan", "Marlon", "Kent", "Alex", "Harvey", "Victor", "Olivia", "Krobus", "Wizard", "Gus", "Elliott", "Haley", "Jodi", "Sam", "Maru", "Pierre", "Shane", "Vincent", "Demetrius", "Clint", "Robin", "Dwarf"],
    },

"NameLocalization": { 
    // "es": "",
    "ko": "주먹밥",
    // "de": "",
    // "fr": "",
    // "hu": "",
    // "it": "",
    // "ja": "",
    // "pt": "",
    // "ru": "",
    // "tr": "",
    "zh": "饭团",
    },
"DescriptionLocalization": { 
    // "es": "",
    "ko": "고기로 속을 채우고 김으로 싼 주먹밥. 낚시에 좋은 간식.",
    // "de": "",
    // "fr": "",
    // "hu": "",
    // "it": "",
    // "ja": "",
    // "pt": "",
    // "ru": "",
    // "tr": "",
    "zh": "包着海苔的肉馅米饭团。",
    },

}