{
	"Name":"Icreon",
	"Description":"An ancient blade used by a band of cultists worshipping a deity with a green tail. Discovered to be commonly used in their rituals.",
	"Type":"sword",
	"PurchasePrice":50000,
	"MinimumDamage":70,
	"MaximumDamage":120,
	"Knockback":2.0,
	"Speed":15,
	"Accuracy":90,
	"Defense":10,
	"MineDropVar":0,
	"MineDropMinimumLevel":-1,
	"ExtraSwingArea":-1,
	"CritChance":0.5,
	"CritMultiplier":2,
	"NameLocalization":{
		"zh":"埃克里昂"
	},
	"DescriptionLocalization":{
		"zh":"由一群崇拜绿尾神的邪教教徒使用的一种古代武器，常用于邪教仪式中。"
	}
}