{
  "Name": "Neapolitan Sundae",
  "Description": "Strawberry! Chocolate! Vanilla! Now you can have them all!",
  "Category": "Cooking",
  "Edibility": 48,
  "Price": 250,
  "IsColored": false,
  "Recipe":
    {
        "ResultCount": 1,
        "Ingredients": [
        {
            "Object": "Strawberry Ice Cream",
            "Count": 1,
        },
        {
            "Object": "Vanilla Ice Cream",
            "Count": 1,
        },
        {
            "Object": "Chocolate Ice Cream",
            "Count": 1,
        },
        ],
        "CanPurchase": true,
"PurchaseFrom": "Gus",
"PurchasePrice": 200,
"PurchaseRequirements": null,
    },
    "EnableWithMod": "ppja.artisanvalleymachinegoods",
   "GiftTastes":
    {
        "Love": ["Vincent", "Jas", "Haley", "Demetrius"],
        "Like": ["Evelyn", "Caroline", "Jodi", "Linus", "Penny", "Sandy", "Clint", "George", "Sebastian", "Abigial", "Alex", "Dwarf", "Elliott", "Gus", "Harvey", "Kent", "Lewis", "Maru", "Pam", "Pierre", "Robin", "Sam", "Shane", "Wizard", "Marnie"],
        "Dislike": ["Emily", "Leah", "Krobus", "Willy"]
    },
  "NameLocalization": { 
		// "es": "",
		"ko": "나폴리탄 선데",
        //"de": "",
        // "fr": "",
        // "hu": "",
        // "it": "",
        //"ja": "",
        //"pt": "a",
        // "ru": "",
        // "tr": "",
        "zh": "三色圣代",
    },
    "DescriptionLocalization":
    {
        // "es": "",
        "ko": "딸기! 초콜렛! 바닐라! 전부 다 먹을 수 있어요!",
        //"de": "",
        // "fr": "",
        // "hu": "",
        // "it": "",
        //"ja": "",
        //"pt": "",
        // "ru": "",
        // "tr": "",
        "zh": "草莓！巧克力！香草！现在你可以将它们全部收入口中！",
    }  
}