{
    "Name": "Rime Witch Hat",
    "FrontHat": {
        "DisableGrayscale": "true",
        "StartingPosition": {
            "X": 0,
            "Y": 0,
        },
        "HeadPosition": {
            "X": -2,
            "Y": -1,
        },
        "HatSize": {
            "Width": 16,
            "Length": 20
          },
    },
    "RightHat": {
        "DisableGrayscale": "true",
        "StartingPosition": {
            "X": 0,
            "Y": 20       
         },
         "HeadPosition": {
            "X": -1,
            "Y": 0,
        },
        "HatSize":{
            "Width": 16,
            "Length": 20
          },
    },
    "LeftHat": {
        "DisableGrayscale": "true",
        "StartingPosition": {
            "X": 0,
            "Y": 40       
         },
         "HeadPosition": {
            "X": -4,
            "Y": 0,
        },
        "HatSize": {
            "Width": 16,
            "Length": 20
          },
    },
    "BackHat": {
        "DisableGrayscale": "true",
        "StartingPosition": {
            "X": 0,
            "Y": 60       
         },
         "HeadPosition": {
            "X": -2,
            "Y": -2,
        },
        "HatSize": {
            "Width": 16,
            "Length": 20
          },
    }
}