{
    "Name": "Gilded Quill",
    "Description": "A marvelous, radiant golden quill. It’s inherently more valuable than other feathers. Parrots only give these to trusted friends!",
    "Category": "AnimalGoods",
    "Edibility": -300,
    "Price": 1500,
    "IsColored": false,
    "Recipe": null,
    "GiftTastes":
	{
        "Love": ["Elliott", "Leo"],
        "Like": ["Emily"],
	"Neutral": ["Caroline", "Clint", "Demetrius", "Dwarf", "Evelyn", "George", "Gus", "Haley", "Harvey", "Jas", "Jodi", "Kent", "Krobus", "Lewis", "Linus", "Marnie", "Maru", "Pam", "Pierre", "Robin", "Sandy", "Sebastian", "Shane", "Vincent", "Willy", "Wizard"],
	"Dislike": ["Penny"]
	},
	"NameLocalization": //Used for localization. 
        { 
            "zh": "镀金羽毛笔", //Chinese (Simplified)
        },
        "DescriptionLocalization": //Used for localization. 
        { 
            "zh": "一根闪闪发光的金色羽毛羽毛。它天生就比其他羽毛更有价值。鹦鹉只把这些送给值得信赖的朋友！", //Chinese (Simplified)
        }
}