{
  "Name": "Crystal Cream Soda",
  "Description": "A pretty, blue colored soda that tastes even better with vanilla.",
  "Category": "ArtisanGoods",
  "Edibility": 130,
  "EdibleIsDrink": true,
    "EdibleBuffs":
    {
        "Farming": 0,
        "Fishing": 0,
        "Mining": 0,
        "Luck": 1,
        "Foraging": 0,
        "MaxStamina": 0,
        "MagnetRadius": 1,
        "Speed": 0,
        "Defense": 0,
        "Attack": 1,
        "Duration": 360,
    },
  "Price": 300,
  "IsColored": false,
  "Recipe": null,
  "GiftTastes": {
    "Love": ["Vincent", "Jas"],
  "Like": ["Abigail", "Alex", "Caroline", "Clint", "Demetrius", "Dwarf", "Elliott", "Emily", "Evelyn", "George", "Gus", "Haley", "Harvey", "Jodi", "Kent", "Leah", "Lewis", "Linus", "Marnie", "Maru", "Pam", "Penny", "Pierre", "Robin", "Sam", "Sandy", "Sebastian", "Shane", "Wizard"],
  "Dislike": ["Krobus", "Willy"],
  },
  "NameLocalization":
    {
        "zh": "水晶果奶油苏打水", //Chinese (Simplified)
    },
    "DescriptionLocalization":
    {
        "zh": "一瓶美丽的蓝色苏打水，尝起来甚至胜过香草自身。", //Chinese (Simplified)
    }
}