{
  "Name": "Vegetable Tempura",
  "Description": "Crisp-tender vegetables fried with a light batter",
  "Category": "Cooking",
  "Edibility": 54,
  "EdibleIsDrink": false,
  "EdibleBuffs": null,
  "Price": 735,
  "IsColored": false,
  "Recipe": {
    "ResultCount": 1,
    "Ingredients": [
      {
        "Object": "Summer Squash",
        "Count": 1,
      },
      {
        "Object": 247,
        "Count": 1,
      },
      {
        "Object": 246,
        "Count": 1,
      },
	  {
        "Object": 188,
        "Count": 1,
      }
    ],
    "CanPurchase": true,
    "PurchaseFrom": "Gus",
    "PurchasePrice": 2735,
  },
  "GiftTastes": {
	"Love": ["Elliott"],
	"Like": ["Abigail", "Alex", "Caroline", "Clint", "Krobus", "Maru", "Shane", "Willy", "Demetrius", "Dwarf", "Sandy", "Emily", "Evelyn", "George", "Gus", "Haley", "Harvey", "Jas", "Jodi", "Kent", "Leah", "Lewis", "Linus", "Marnie", "Pam", "Penny", "Pierre", "Robin", "Sam", "Sebastian", "Vincent", "Wizard"],
  },
  "NameLocalization":{
        "zh": "炸蔬菜天妇罗", //Chinese (Simplified)
    },
    "DescriptionLocalization":
    {
        "zh": "将蔬菜裹上面糊炸制而成，口感外酥里嫩。广为人知的日式餐品，但『天妇罗』最早其实是源自于葡萄牙的传统菜肴。", //Chinese (Simplified)
    },
}