{
  "Name": "Bee Balm Cream Soda",
  "Description": "The sweet, herbal aroma makes your mouth water.",
  "Category": "ArtisanGoods",
  "Edibility": 70,
  "EdibleIsDrink": true,
    "EdibleBuffs":
    {
        "Farming": 1,
        "Fishing": 1,
        "Mining": 0,
        "Luck": 0,
        "Foraging": 0,
        "MaxStamina": 0,
        "MagnetRadius": 0,
        "Speed": 0,
        "Defense": 0,
        "Attack": 0,
        "Duration": 360,
    },
  "Price": 280,
  "IsColored": false,
  "Recipe": null,
  "GiftTastes": {
    "Love": ["Haley", "Harvey", "Marnie", "Sandy"],
    "Like": ["Abigail", "Alex", "Caroline", "Clint", "Demetrius", "Dwarf", "Elliott", "Emily", "Evelyn", "George", "Gus", "Jas", "Kent", "Krobus", "Leah", "Lewis", "Linus", "Maru", "Pam", "Penny", "Pierre", "Robin", "Sam", "Sebastian", "Shane", "Willy", "Wizard"],
    "Neutral": ["Jodi"],
    "Dislike": ["Vincent"],
  },
  "NameLocalization": {
	// "es": "",
    "ko": "멜리사 크림 소다",
    // "de": "",
    // "fr": "",
    // "hu": "",
    // "it": "",
    // "ja": "",
    "pt": "Refrigerante Cremoso de Monarda",
    // "ru": "",
    // "tr": "",
    "zh":"香蜂花奶油苏打水",
  },
  "DescriptionLocalization": {
	// "es": "",
    "ko": "달콤한 허브 향이 군침돕니다.",
    // "de": "",
    // "fr": "",
    // "hu": "",
    // "it": "",
    // "ja": "",
    "pt": "O aroma doce de ervas te deixa com água na boca.",
    // "ru": "",
    // "tr": "",
    "zh":"一股香甜的花草香气让你口舌生津。",
  },
"EnableWithMod": "mizu.flowers",
    "ContextTags": [
    	"soda_item"
 ]
}