{
  "Name": "Beret (Prismatic)",
  "FrontHat": {
    "IsPrismatic": true,
    "DisableGrayscale": false,
    "ColorMasks": [
      [ 177, 177, 177],
	  [ 146, 146, 146], 
	  [ 138, 138, 138],
	  [ 121, 121, 121],
	  [ 105, 105, 105],
	  [ 96, 96, 96]
    ],
    "StartingPosition": {
      "X": 0,
      "Y": 0
    },
    "HeadPosition": {
      "X": 0,
      "Y": 0
    },
    "HatSize": {
      "Width": 20,
      "Length": 20
    }
  },
  "RightHat": {
    "IsPrismatic": true,
    "HideHair": false,
    "DisableGrayscale": false,
    "ColorMasks": [
      [ 177, 177, 177],
	  [ 146, 146, 146], 
	  [ 138, 138, 138],
	  [ 121, 121, 121],
	  [ 105, 105, 105],
	  [ 96, 96, 96]
    ],
    "StartingPosition": {
      "X": 0,
      "Y": 20
    },
    "HeadPosition": {
      "X": 0,
      "Y": 0
    },
    "HatSize": {
      "Width": 20,
      "Length": 20
    }
  },
   "LeftHat": {
	"IsPrismatic": true,
    "HideHair": false,
    "DisableGrayscale": false,
    "ColorMasks": [
      [ 177, 177, 177],
	  [ 146, 146, 146], 
	  [ 138, 138, 138],
	  [ 121, 121, 121],
	  [ 105, 105, 105],
	  [ 96, 96, 96]
    ],
    "StartingPosition": {
      "X": 0,
      "Y": 40
    },
    "HeadPosition": {
      "X": 0,
      "Y": 0
    },
    "HatSize": {
      "Width": 20,
      "Length": 20
    }
  },
  "BackHat": {
    "IsPrismatic": true,
    "HideHair": false,
    "DisableGrayscale": false,
    "ColorMasks": [
      [ 177, 177, 177],
	  [ 146, 146, 146], 
	  [ 138, 138, 138],
	  [ 121, 121, 121],
	  [ 105, 105, 105],
	  [ 96, 96, 96]
    ],
    "StartingPosition": {
      "X": 0,
      "Y": 60
    },
    "HeadPosition": {
      "X": 0,
      "Y": 0
    },
    "HatSize": {
      "Width": 20,
      "Length": 20
    }
  }
}