{
  "Name": "White Chocolate",
  "Description": "A sweet chocolate made with cocoa butter and milk.",
  "Category": "ArtisanGoods",
  "Edibility": 40,
  "Price": 552,
  "IsColored": false,
  "Recipe": null,
  "GiftTastes":
    {
		"Love": ["Haley", "Jas", "Marnie"],
        "Like": ["Abigail", "Alex", "Caroline", "Clint", "Demetrius", "Elliott", "Emily", "Evelyn", "Gus", "Jodi", "Kent", "Leah", "Lewis", "Linus", "Maru", "Pam", "Penny", "Pierre", "Robin", "Sam", "Sandy", "Shane", "Vincent", "Wizard"],
		"Dislike": ["Dwarf", "George", "Harvey", "Krobus", "Sebastian"],
		"Hate": ["Willy"],
},

// translation
  "NameLocalization":
  {
	// "es": "",
     "ko": "화이트 초콜렛",
     "de": "Weiße Schokolade",
    // "fr": "",
    // "hu": "",
    // "it": "",
    // "ja": "",
    // "pt": "",
    // "ru": "",
    // "tr": "",
     "zh": "白巧克力",
  },
  "DescriptionLocalization":
  {
	// "es": "",
     "ko": "코코아버터와 우유로 만든 달콤한 초콜렛.",
     "de": "Eine süße Schokolade aus Kakaobutter und Milch.",
    // "fr": "",
    // "hu": "",
    // "it": "",
    // "ja": "",
    // "pt": "",
    // "ru": "",
    // "tr": "",
     "zh": "用可可黄油以及牛奶做出来的甜巧克力。拥有着跟牛奶巧克力不相上下的浓郁奶香，巧克力中的甜度王者。",
  }
}