{
  "Name": "Lemon Blueberry Cake",
  "Description": "A slice of light lemon cake with lemon frosting and a light drizzle of blueberry glaze.",
  "Category": "Cooking",
  "Edibility": 32,
  "EdibleIsDrink": false,
  "EdibleBuffs": null,
  "Price": 400,
  "IsColored": false,
  "Recipe": {
    "ResultCount": 1,
    "Ingredients": [
      {
        "Object": 246,
        "Count": 1
      },
      {
        "Object": 245,
        "Count": 1
      },
      {
        "Object": -5,
        "Count": 1
      },
      {
        "Object": "Lemon",
        "Count": 1
      },
      {
        "Object": 258,
        "Count": 1
      }
    ],
    "CanPurchase": true,
    "PurchaseFrom": "Gus",
    "PurchasePrice": 850,
    "PurchaseRequirements": null
  },
    "GiftTastes": {
      "Love": [ "Haley", "Jas", "Marnie", "Vincent", "Abigail", "Evelyn", "Jodi" ],
      "Like": [ "Alex", "Caroline", "Clint", "Demetrius", "Dwarf", "Elliott", "Emily", "George", "Gus", "Harvey", "Kent", "Leah", "Lewis", "Linus", "Maru", "Pam", "Penny", "Pierre", "Robin", "Sam", "Sandy", "Sebastian", "Shane", "Wizard" ],
      "Dislike": [ "Krobus", "Willy" ]
    },
  "NameLocalization": { 
		// "es": "",
		"ko": "레몬 블루베리 케이크",
        //"de": "",
        // "fr": "",
        // "hu": "",
        // "it": "",
        //"ja": "",
        //"pt": "",
        // "ru": "",
        // "tr": "",
        //"zh": "",
    },
    "DescriptionLocalization": {
        // "es": "",
        "ko": "레몬 프로스팅과 블루베리 글레이즈를 살짝 뿌린 가벼운 레몬 케이크 한 조각.",
        //"de": "",
        // "fr": "",
        // "hu": "",
        // "it": "",
        //"ja": "",
        //"pt": "",
        // "ru": "",
        // "tr": "",
        // "zh": "",
    }  
}