{
	"Name": "Sliced Pepperoni Deluxe Pizza",
	"Description": "A more tasteful pepperoni pizza.",
	"Category": "ArtisanGoods",
	"Edibility": 10,
	"Price": 120,
	"IsColored": false,
	"Recipe": null,

	"GiftTastes":
	{
		"Love": ["Sam", "Shane", "Alex", "Gus"],
		"Like": ["Abigail", "Caroline", "Clint", "Demetrius", "Dwarf", "Emily", "Evelyn", "George", "Haley", "Jas", "Jodi", "Kent", "Lewis", "Linus", "Marnie", "Maru", "Pam", "Penny", "Pierre", "Robin", "Sandy", "Sebastian", "Vincent", "Wizard"],
		"Dislike": ["Elliott", "Harvey", "Krobus", "Leo", "Willy"],
		"Hate": ["Leah"],
	},

	"NameLocalization":
	{
			// "es": "",
			"ko": "페퍼로니 디럭스 조각 피자",
			// "de": "",
			// "fr": "",
			// "hu": "",
			// "it": "",
			"ja": "デラックスペパロニピザスライス",
			// "pt": "",
			// "ru": "",
			// "tr": "",
			"zh": "切片意大利辣香肠豪华披萨"
	},
	"DescriptionLocalization":
	{
			// "es": "",
			"ko": "더 맛있는 페퍼로니 조각 피자.",
			// "de": "",
			// "fr": "",
			// "hu": "",
			// "it": "",
			"ja": "ペパロニピザの贅沢なバージョン。",
			// "pt": "",
			// "ru": "",
			// "tr": "",
			"zh": "更美味的意大利辣香肠披萨"
	}
}
