{
	"Name": "Red Plate Pizza",
	"Description": "Get your antioxidants here.",
	"Category": "Cooking",
  
	"Edibility": 101,
	"EdibleIsDrink": false,
	"EdibleBuffs": {
					"Farming": 0,
					"Fishing": 0,
					"Mining": 0,
					"Luck": 0,
					"Duration": 180, 
					"Foraging": 0,
					"MaxStamina": 50,
					"MagnetRadius": 0,
					"Speed": 0,
					"Defense": 0,
					"Attack": 0,
  },
  
	"Price": 400,
  
	"IsColored": false,
  
	"Recipe": {
			  "ResultCount": 1,
			  
			  "Ingredients": [
								{
								   "Object": "Pizza Base",
								   "Count": 1,
								},
								{
								   "Object": 424,
								   "Count": 1,
								},
								{
								   "Object": 230,
								   "Count": 1,
								},
			      ],
			   
			   "IsDefault": "False",
},
			"GiftTastes": { 
					"Love": [ "Freddie","Kenneth","Lenny","Lola","Penny"], 
					"Dislike": [  "Jessie" ],	
	},
	"NameLocalization":
    {
        "zh": "红之盛宴披萨",
    },
    "DescriptionLocalization":
    {
        "zh": "从中可以获取丰富的抗氧化物质",
    },			
}