{
    "Name": "Muscadine Soda",
    "Description": "A non-alcoholic wine grape-flavoured soda. Fancy!",
    "Category": "ArtisanGoods",
    "Edibility": 160,
    "EdibleIsDrink": true,
    "EdibleBuffs":
    {
        "Farming": 0,
        "Fishing": 0,
        "Mining": 0,
        "Luck": 2,
        "Foraging": 2,
        "MaxStamina": 0,
        "MagnetRadius": 0,
        "Speed": 0,
        "Defense": 0,
        "Attack": 0,
        "Duration": 360,
    },
    "Price": 300,
    "IsColored": false,
    "Recipe": null,
    "GiftTastes": {
    "Love": ["Harvey", "Leah"],
	"Like": ["Abigail", "Alex", "Caroline", "Clint", "Demetrius", "Dwarf", "Elliott", "Emily", "Evelyn", "George", "Gus", "Haley", "Jodi", "Kent", "Lewis", "Linus", "Marnie", "Maru", "Pam", "Penny", "Pierre", "Robin", "Sam", "Sandy", "Sebastian", "Shane", "Wizard"],
	"Dislike": ["Vincent", "Jas", "Krobus", "Willy"],
	},
    "NameLocalization":
    {
        //"es": "",
        //"ko": "",
        //"de": "",
        //"fr": "",
        //"hu": "",
        //"it": "",
        //"ja": "",
        //"pt": "",
        //"ru": "",
        //"tr": "",
        "zh":"圆叶葡萄苏打",
    },
    "DescriptionLocalization":
    {
        //"es": "",
        //"ko": "",
        //"de": "",
        //"fr": "",
        //"hu": "",
        //"it": "",
        //"ja": "",
        //"pt": "",
        //"ru": "",
        //"tr": "",
        "zh":"一种不含酒精的葡萄味汽水。幻想!",
    },
	"ContextTags": [
	"soda_item"
	 ]
}