{
	"Name": "Tumbleweed",
	"Type": "Jumping",
	"EnableFarmerCollision": true,
	"EnableShadow": true,
	"Shadow": {
		"OffsetX": -4,
		"OffsetY": 4,
		"Scale": 1.5,
		"Alpha": 96
	},
	"TravelSpeed": 4,
	"SpawnDirection": 3,
	"MaxIdleDistance": -1,
	"MaxDistanceBeforeTeleport": -1,
	"InspectionDialogue": "天哪，这附近真的很忙",
	"FrameSizeWidth": 32,
	"FrameSizeHeight": 48,
	"IdleBehavior": "PACING",
	"IdleArguments": [
		300,
		0
	],
	"UpAnimation": {
		"StartingFrame": 0,
		"NumberOfFrames": 12,
		"Duration": 100,
		"IdleAnimation": {
			"StartingFrame": 0,
			"NumberOfFrames": 12,
			"Duration": 100
		}
	}
,
	"DownAnimation": {
		"StartingFrame": 0,
		"NumberOfFrames": 12,
		"Duration": 100,
		"IdleAnimation": {
			"StartingFrame": 0,
			"NumberOfFrames": 12,
			"Duration": 100
		}
	}
,
	"LeftAnimation": {
		"StartingFrame": 0,
		"NumberOfFrames": 12,
		"Duration": 100,
		"IdleAnimation": {
			"StartingFrame": 0,
			"NumberOfFrames": 12,
			"Duration": 100
		}
	}
,
	"RightAnimation": {
		"StartingFrame": 0,
		"NumberOfFrames": 12,
		"Duration": 100,
		"IdleAnimation": {
			"StartingFrame": 0,
			"NumberOfFrames": 12,
			"Duration": 100
		}
	}
}