{
	//Days of Week
	"Mon": "900 Custom_DTZ_JojaCEO 5 28 0 \"Strings\\schedules\\Kristoff:wash.1\"/930 Custom_DTZ_JojaCEO 9 22 0 \"Strings\\schedules\\Kristoff:job.1\"/1040 Custom_DTZ_JojaOffices 13 7 2 \"Strings\\schedules\\Kristoff:job.2\"/1300 Custom_DTZ_ZuzuCityCrossroads1 17 22 0 \"Strings\\schedules\\Kristoff:job.3\"/1500 Custom_DTZ_JojaMini 13 14 2 \"Strings\\schedules\\Kristoff:job.4\"/1630 Custom_DTZ_JojaOffices 1 16 1 \"Strings\\schedules\\Kristoff:job.2\"/1900 Custom_DTZ_JojaElevHall 10 10 0/1930 Custom_DTZ_JojaElevHall 12 10 0/2000 Custom_DTZ_JojaElevHall 14 10 0/2030 Custom_DTZ_JojaElevHall 16 10 0/2100 Custom_DTZ_JojaCEO 29 12 2/2210 Custom_DTZ_JojaCEO 4 5 2",
	"Tue": "910 Custom_DTZ_JojaCEO 1 5 0/1100 Custom_DTZ_JojaHQCafe 1 8 1/1320 Custom_DTZ_JojaMini 13 14 2 \"Strings\\schedules\\Kristoff:job.4\"/1630 Custom_DTZ_JojaOffices 1 16 1 \"Strings\\schedules\\Kristoff:job.2\"/1900 Custom_DTZ_JojaElevHall 10 10 0/1930 Custom_DTZ_JojaElevHall 12 10 0/2000 Custom_DTZ_JojaElevHall 14 10 0/2030 Custom_DTZ_JojaElevHall 16 10 0/2100 Custom_DTZ_JojaCEO 29 12 2/2230 Custom_DTZ_JojaCEO 4 5 2",
	"Wed": "840 Custom_DTZ_JojaCEO 5 28 0 \"Strings\\schedules\\Kristoff:wash.1\"/920 Custom_DTZ_JojaCEO 9 22 0 \"Strings\\schedules\\Kristoff:job.1\"/1000 Custom_DTZ_JojaOffices 13 7 2 \"Strings\\schedules\\Kristoff:job.2\"/1240 Custom_DTZ_ZuzuCityCrossroads1 17 22 0 \"Strings\\schedules\\Kristoff:job.3\"/1510 Custom_DTZ_JojaMini 13 14 2 \"Strings\\schedules\\Kristoff:job.4\"/1640 Custom_DTZ_JojaOffices 1 16 1 \"Strings\\schedules\\Kristoff:job.2\"/1900 Custom_DTZ_JojaElevHall 10 10 0/1930 Custom_DTZ_JojaElevHall 12 10 0/2000 Custom_DTZ_JojaElevHall 14 10 0/2030 Custom_DTZ_JojaElevHall 16 10 0/2200 Custom_DTZ_JojaCEO 29 12 2/2250 Custom_DTZ_JojaCEO 4 5 2",
	"Thu": "1000 Custom_DTZ_JojaCEO 29 12 2/1200 Custom_DTZ_JojaCEO 11 22 1/1300 Custom_DTZ_JojaOffices 13 7 2 \"Strings\\schedules\\Kristoff:job.2\"/1640 Custom_DTZ_JojaOffices 1 16 1 \"Strings\\schedules\\Kristoff:job.2\"/1830 Custom_DTZ_JojaElevHall 10 10 0/1930 Custom_DTZ_JojaElevHall 12 10 0/2000 Custom_DTZ_JojaElevHall 14 10 0/2030 Custom_DTZ_JojaElevHall 16 10 0/2200 Custom_DTZ_JojaCEO 29 12 2/2250 Custom_DTZ_JojaCEO 4 5 2",
	"Fri": "GOTO Mon",
	"Sat": "GOTO Thu",
	"Sun": "GOTO Tue",
	"rain": "GOTO Thu"
}