{
	"Name": "Raincoat",
	"Description": "My hair is beautiful and dry.",
	"Price": 1,
	"PurchasePrice": 35,
	"ShowHair": false,
	"IgnoreHairstyleOffset": true,
	"NameLocalization":
    {
         "es": "Capa de lluvia",
         "ko": "비옷",
         "de": "Regenjacke",
         "fr": "Imperméable",
         "hu": "Esőkabát",
         "it": "Impermeabile",
         "ja": "レインコート",
         "pt": "Capa de chuva",
         "ru": "Плащ дождевик",
         "tr": "Yağmurluk",
         "zh": "雨衣",
    },
    "DescriptionLocalization":
    {
         "es": "Mi cabello es hermoso y seco.",
         "ko": "내 머리카락은 아름답고 건조합니다.",
         "de": "Meine Haare sind schön und trocken.",
         "fr": "Mes cheveux sont beaux et secs.",
         "hu": "Szép és száraz a hajam.",
         "it": "I miei capelli sono belli e asciutti.",
         "ja": "私の髪は美しくて乾いています。",
         "pt": "Meu cabelo lindo e seco.",
         "ru": "Мои волосы красивые и сухие.",
         "tr": "Saçlarım güzel ve kuru.",
         "zh": "我的头发又漂亮又干。",
    },
}