{
    "Name": "White Alpine Strawberry",
    "Product": "White Alpine Strawberry",
    "SeedName": "White Alpine Strawberry Seeds",
    "SeedDescription": "Plant these in spring. Takes 10 days to mature, and continues to produce.",
    "Type": "Vegetable",

    "Seasons": ["spring"],
    "Phases": [ 1, 2, 2, 2, 3, ],
    "RegrowthPhase": 2,
    "HarvestWithScythe": false,
    "TrellisCrop": false,
    "Colors": null,
    "Bonus": {
        "MinimumPerHarvest": 1,
        "MaximumPerHarvest": 4,
        "MaxIncreasePerFarmLevel": 5,
        "ExtraChance": 0.1,
    },

    "SeedPurchasePrice": 80,
    "SeedNameLocalization":
    {
        "zh": "白色高山草莓种子", //Chinese (Simplified)
    },
    "DescriptionLocalization":
    {
        "zh": "春季种植，需要10天时间成熟，之后可循环收获。", //Chinese (Simplified)
    },
}
