[
{
    "ProducerName": "Seed Maker",
    "InputIdentifier": "Mistletoe Clump",
    "InputStack": 1,
    "MinutesUntilReady": 20,
    "OutputIdentifier": "Mistletoe Berries",
    "OutputStack": 1,
    "Sounds": ["Ship"],
  },
{
    "ProducerName": "Seed Maker",
    "InputIdentifier": "Vanilla Orchid",
    "InputStack": 1,
    "MinutesUntilReady": 20,
    "OutputIdentifier": "Vanilla Beans",
    "OutputStack": 1,
    "Sounds": ["Ship"],
  },
{
    "ProducerName": "Wood Chipper",
    "InputIdentifier": "Spanish Moss",
    "InputStack": 1,
    "MinutesUntilReady": 60,
    "OutputIdentifier": "771",
    "OutputStack": 5,
    "Sounds": ["Ship"],
  },
{
    "ProducerName": "Wood Chipper",
    "InputIdentifier": "Reindeer Lichen",
    "InputStack": 1,
    "MinutesUntilReady": 30,
    "OutputIdentifier": "297",
    "OutputStack": 3,
    "Sounds": ["Ship"],
  },
{
    "ProducerName": "Loom",
    "InputIdentifier": "Spanish Moss",
    "InputStack": 1,
    "MinutesUntilReady": 360,
    "OutputIdentifier": "Spanish Moss Thread",
    "OutputStack": 1,
    "Sounds": ["Ship"],
  },
{
    "ProducerName": "Oil Maker",
    "InputIdentifier": "Vanilla Beans",
    "InputStack": 1,
    "MinutesUntilReady": 120,
    "OutputIdentifier": "Vanilla Flavoring",
    "OutputStack": 1,
    "Sounds": ["Ship"],
  },
{
    "ProducerName": "Furnace",
    "InputIdentifier": "Reindeer Lichen",
    "InputStack": 3,
    "FuelIdentifier": "382",
    "FuelStack": 1,
    "MinutesUntilReady": 120,
    "OutputIdentifier": "Lichen Bread",
    "OutputStack": 1,
    "Sounds": ["Ship"],
  },

// Optional recipe if Strange Machines is installed
{
    "ProducerName": "Fertilizer Maker",
    "InputIdentifier": "Reindeer Lichen",
    "InputStack": 3,
    "FuelIdentifier": "571",
    "FuelStack": 2,
    "MinutesUntilReady": 360,
    "OutputIdentifier": "877",
    "OutputStack": 10,
    "Sounds": ["Ship"],
  },
]