{
	"Name": "Scalloped Potatoes LF",
	"Description": "Tender sliced potatoes layered in a bed of rich, creamy, cheese sauce.",
	"Category": "Cooking",
	"Edibility": 135,
    "TranslationKey": "scalloped-potatoes-lf",
	"EdibleIsDrink": false,
	"EdibleBuffs": 
	{
        "Farming": 3,
        "Fishing": 0,
        "Mining": 0,
        "Luck": 0,
        "Foraging": 3,
        "MaxStamina": 50,
        "MagnetRadius": 0,
        "Speed": 0,
        "Defense": 0,
        "Attack": 0,
        "Duration": 880,
    },
	"Recipe":
    {
    "ResultCount": 1,
    "Ingredients": [ { "Object": "Potato", "Count": 3}, { "Object": "Emmental LF", "Count": 1 },{ "Object": "Parmesan LF", "Count": 1 }, { "Object": "Garlic", "Count": 1 }, { "Object": -6, "Count": 1 } ],
    "CanPurchase": false,
    "PurchaseFrom": "Joseph",
    "PurchasePrice": 1200,
    "PurchaseRequirements": [ "" ],
    },
	"CanSell": true,
	"Price": 325,
	"IsColored": false,
	"GiftTastes":
	{
	    "Love": [ "George", "Kent", "Sam"],
		"Like": [ "Linus", "Joseph", "Alex", "Shane", "MorrisTod", "GuntherSilvian" ],
		"Dislike": [ "Paisley", "Haley", "Harvey", "Jodi", "Leah", "Pierre", "Willy" ],
		"Hate": [ "Jas", "Vincent", "Susan", "Morgan", "Evelyn", "Sebastian" ]
	},
}