{
	"events":
	[
		{
			"name": "送货帮助 (两心)",
			"location": "BusStop",
			"eventId":"75160146",
      			"night": false,
     			"mail": null
		},
		{
			"name": "放松 (四心)",
			"location": "Custom_Ridgeside_RSVCliff",
			"eventId":"75160147",
      			"night": false,
     			"mail": null
		},
		{
			"name": "焦急等待 (六心)",
			"location": "Custom_Ridgeside_LennyHouse",
			"eventId":"75160148",
      			"night": false,
     			"mail": null
		},
		{
			"name": "检查信件 (八心)",
			"location": "Custom_Ridgeside_RidgesideVillage",
			"eventId":"75160149",
      			"night": false,
     			"mail": null
		},
		{
			"name": "回家晚了 (十心)",
			"location": "Custom_Ridgeside_RSVCliff",
			"eventId":"75160150",
      			"night": false,
     			"mail": null
		},
		{
			"name": "疲惫 (十四心 Part 1)",
			"location": "FarmHouse",
			"eventId":"75160227",
      			"night": false,
     			"mail": null
		},
		{
			"name": "课程 (十四心 Part 2)",
			"location": "ArchaeologyHouse",
			"eventId":"75160228",
      			"night": false,
     			"mail": null
		}

	]
}