[
	{
		"$ItemType": "Furniture",
		"ID": "SingleShelfPink",
		"Type": "Painting",
		"Configurations": [
			{
				"Texture": "assets/SingleShelfPink.png",
				"DisplaySize": {
					"X": 3,
					"Y": 1
				},
				"CollisionHeight": 1
			},
		]
	},	
	{
		"$ItemType": "ShopEntry",
		"ShopId": "Carpenter",
		"Cost": 400,
		"Item": {
			"Type": "DGAItem",
			"Value": "StarAmy.BakeryDisplays/SingleShelfPink"
		}
	},	
	{
		"$ItemType": "Furniture",
		"ID": "DoubleShelfPink",
		"Type": "Painting",
		"Configurations": [
			{
				"Texture": "assets/DoubleShelfPink.png",
				"DisplaySize": {
					"X": 3,
					"Y": 2
				},
				"CollisionHeight": 2
			},
		]
	},	
	{
		"$ItemType": "ShopEntry",
		"ShopId": "Carpenter",
		"Cost": 800,
		"Item": {
			"Type": "DGAItem",
			"Value": "StarAmy.BakeryDisplays/DoubleShelfPink"
		}
	},	
	{
		"$ItemType": "Furniture",
		"ID": "TripleShelfPink",
		"Type": "Painting",
		"Configurations": [
			{
				"Texture": "assets/TripleShelfPink.png",
				"DisplaySize": {
					"X": 3,
					"Y": 3
				},
				"CollisionHeight": 3
			},
		]
	},	
	{
		"$ItemType": "ShopEntry",
		"ShopId": "Carpenter",
		"Cost": 1200,
		"Item": {
			"Type": "DGAItem",
			"Value": "StarAmy.BakeryDisplays/TripleShelfPink"
		}
	},
	{
		"$ItemType": "Furniture",
		"ID": "SmallShelfPink",
		"Type": "Painting",
		"Configurations": [
			{
				"Texture": "assets/SmallShelfPink.png",
				"DisplaySize": {
					"X": 1,
					"Y": 3
				},
				"CollisionHeight": 3
			},
		]
	},	
	{
		"$ItemType": "ShopEntry",
		"ShopId": "Carpenter",
		"Cost": 400,
		"Item": {
			"Type": "DGAItem",
			"Value": "StarAmy.BakeryDisplays/SmallShelfPink"
		}
	},
	{
		"$ItemType": "Furniture",
		"ID": "MediumShelfPink",
		"Type": "Painting",
		"Configurations": [
			{
				"Texture": "assets/MediumShelfPink.png",
				"DisplaySize": {
					"X": 2,
					"Y": 3
				},
				"CollisionHeight": 3
			},
		]
	},	
	{
		"$ItemType": "ShopEntry",
		"ShopId": "Carpenter",
		"Cost": 800,
		"Item": {
			"Type": "DGAItem",
			"Value": "StarAmy.BakeryDisplays/MediumShelfPink"
		}
	},
	{
		"$ItemType": "Furniture",
		"ID": "SingleCakeStandPink",
		"Type": "Decoration",
		"Configurations": [
			{
				"Texture": "assets/SingleCakeStandPink.png",
				"DisplaySize": {
					"X": 1,
					"Y": 1
				},
				"CollisionHeight": 1
			},
	
		]
	},	
	
	{
		"$ItemType": "ShopEntry",
		"ShopId": "Carpenter",
		"Cost": 100,
		"Item": {
			"Type": "DGAItem",
			"Value": "StarAmy.BakeryDisplays/SingleCakeStandPink"
		}
	},
	{
		"$ItemType": "Furniture",
		"ID": "DoubleCakeStandPink",
		"Type": "Decoration",
		"Configurations": [
			{
				"Texture": "assets/DoubleCakeStandPink.png",
				"DisplaySize": {
					"X": 1,
					"Y": 2
				},
				"CollisionHeight": 2
			},
		]
	},	

	{
		"$ItemType": "ShopEntry",
		"ShopId": "Carpenter",
		"Cost": 200,
		"Item": {
			"Type": "DGAItem",
			"Value": "StarAmy.BakeryDisplays/DoubleCakeStandPink"
		}
	},
	{
		"$ItemType": "Furniture",
		"ID": "TripleCakeStandPink",
		"Type": "Decoration",
		"Configurations": [
			{
				"Texture": "assets/TripleCakeStandPink.png",
				"DisplaySize": {
					"X": 1,
					"Y": 3
				},
				"CollisionHeight": 3
			},
	
		]
	},	
	{
		"$ItemType": "ShopEntry",
		"ShopId": "Carpenter",
		"Cost": 300,
		"Item": {
			"Type": "DGAItem",
			"Value": "StarAmy.BakeryDisplays/TripleCakeStandPink"
		}
	},
	{
		"$ItemType": "Furniture",
		"ID": "SmallGlassCasePink",
		"Type": "Decoration",
		"Configurations": [
			{
				"Texture": "assets/SmallGlassCasePink.png",
				"DisplaySize": {
					"X": 1,
					"Y": 3
				},
				"CollisionHeight": 3
			},

		]
	},	
	{
		"$ItemType": "ShopEntry",
		"ShopId": "Carpenter",
		"Cost": 300,
		"Item": {
			"Type": "DGAItem",
			"Value": "StarAmy.BakeryDisplays/SmallGlassCasePink"
		}
	},
	{
		"$ItemType": "Furniture",
		"ID": "MediumGlassCasePink",
		"Type": "Decoration",
		"Configurations": [
			{
				"Texture": "assets/MediumGlassCasePink.png",
				"DisplaySize": {
					"X": 2,
					"Y": 3
				},
				"CollisionHeight": 3
			},
		]
	},	
	{
		"$ItemType": "ShopEntry",
		"ShopId": "Carpenter",
		"Cost": 500,
		"Item": {
			"Type": "DGAItem",
			"Value": "StarAmy.BakeryDisplays/MediumGlassCasePink"
		}
	},
	{
		"$ItemType": "Furniture",
		"ID": "FlatGlassCasePink",
		"Type": "Decoration",
		"Configurations": [
			{
				"Texture": "assets/FlatGlassCasePink.png",
				"DisplaySize": {
					"X": 3,
					"Y": 3
				},
				"CollisionHeight": 3
			},
		]
	},	
	{
		"$ItemType": "ShopEntry",
		"ShopId": "Carpenter",
		"Cost": 700,
		"Item": {
			"Type": "DGAItem",
			"Value": "StarAmy.BakeryDisplays/FlatGlassCasePink"
		}
	},
	{
		"$ItemType": "Furniture",
		"ID": "RoundGlassCasePink",
		"Type": "Decoration",
		"Configurations": [
			{
				"Texture": "assets/RoundGlassCasePink.png",
				"DisplaySize": {
					"X": 3,
					"Y": 3
				},
				"CollisionHeight": 3
			},
		]
	},	
	{
		"$ItemType": "ShopEntry",
		"ShopId": "Carpenter",
		"Cost": 700,
		"Item": {
			"Type": "DGAItem",
			"Value": "StarAmy.BakeryDisplays/RoundGlassCasePink"
		}
	},
		{
		"$ItemType": "Furniture",
		"ID": "SmallCounterPink",
		"Type": "Decoration",
		"Configurations": [
			{
				"Texture": "assets/SmallCounterPink.png",
				"DisplaySize": {
					"X": 1,
					"Y": 2
				},
				"CollisionHeight": 2
			},
		]
	},	
	{
		"$ItemType": "ShopEntry",
		"ShopId": "Carpenter",
		"Cost": 200,
		"Item": {
			"Type": "DGAItem",
			"Value": "StarAmy.BakeryDisplays/SmallCounterPink"
		}
	},
	{
		"$ItemType": "Furniture",
		"ID": "MediumCounterPink",
		"Type": "Decoration",
		"Configurations": [
			{
				"Texture": "assets/MediumCounterPink.png",
				"DisplaySize": {
					"X": 2,
					"Y": 2
				},
				"CollisionHeight": 2
			},
		]
	},	
	{
		"$ItemType": "ShopEntry",
		"ShopId": "Carpenter",
		"Cost": 400,
		"Item": {
			"Type": "DGAItem",
			"Value": "StarAmy.BakeryDisplays/MediumCounterPink"
		}
	},
	{
		"$ItemType": "Furniture",
		"ID": "LargeCounterPink",
		"Type": "Decoration",
		"Configurations": [
			{
				"Texture": "assets/LargeCounterPink.png",
				"DisplaySize": {
					"X": 3,
					"Y": 2
				},
				"CollisionHeight": 2
			},
		]
	},	
	{
		"$ItemType": "ShopEntry",
		"ShopId": "Carpenter",
		"Cost": 600,
		"Item": {
			"Type": "DGAItem",
			"Value": "StarAmy.BakeryDisplays/LargeCounterPink"
		}
	}
]